aism-0.1.0.dist-info/METADATA
aism-0.1.0.dist-info/WHEEL
aism-0.1.0.dist-info/licenses/LICENSE
aism/__init__.py
aism/utils.py
aism/aism.pyi
aism/py.typed
aism/override.py
aism/aism.cpython-312-darwin.so
aism-0.1.0.dist-info/RECORD
