Metadata-Version: 2.3
Name: aism
Version: 0.1.0
Classifier: Programming Language :: Rust
Classifier: Programming Language :: Python :: Implementation :: CPython
Classifier: Programming Language :: Python :: Implementation :: PyPy
Requires-Dist: typing-extensions
License-File: LICENSE
Summary: AI for the runtime.
Keywords: aism,ai,groq,translate,dataclass,autofill,runtime,llm
Requires-Python: >=3.9
Project-URL: Source, https://github.com/AWeirdDev/aism
Project-URL: Issues, https://github.com/AWeirdDev/aism
